class_only_design/__init__.py
class_only_design/api.py
class_only_design/constants.py
class_only_design/meta.py
class_only_design/util.py
class_only_design/tests/__init__.py
class_only_design/tests/test_class_only.py
class_only_design/tests/test_namespace.py
class_only_design/tests/test_util.py
class_only_design-1.0.0.dist-info/licenses/LICENSE
class_only_design-1.0.0.dist-info/METADATA
class_only_design-1.0.0.dist-info/WHEEL
class_only_design-1.0.0.dist-info/top_level.txt
class_only_design-1.0.0.dist-info/RECORD
